odoo9_addon_l10n_ec_config-9.0.1.0.0.99.dev5-py2.7-nspkg.pth
odoo9_addon_l10n_ec_config-9.0.1.0.0.99.dev5.dist-info/METADATA
odoo9_addon_l10n_ec_config-9.0.1.0.0.99.dev5.dist-info/RECORD
odoo9_addon_l10n_ec_config-9.0.1.0.0.99.dev5.dist-info/WHEEL
odoo9_addon_l10n_ec_config-9.0.1.0.0.99.dev5.dist-info/namespace_packages.txt
odoo9_addon_l10n_ec_config-9.0.1.0.0.99.dev5.dist-info/top_level.txt
odoo_addons/l10n_ec_config/README.rst
odoo_addons/l10n_ec_config/__init__.py
odoo_addons/l10n_ec_config/__openerp__.py
odoo_addons/l10n_ec_config/i18n/am.po
odoo_addons/l10n_ec_config/i18n/ar.po
odoo_addons/l10n_ec_config/i18n/bg.po
odoo_addons/l10n_ec_config/i18n/bs.po
odoo_addons/l10n_ec_config/i18n/ca.po
odoo_addons/l10n_ec_config/i18n/ca_ES.po
odoo_addons/l10n_ec_config/i18n/cs.po
odoo_addons/l10n_ec_config/i18n/da.po
odoo_addons/l10n_ec_config/i18n/de.po
odoo_addons/l10n_ec_config/i18n/el_GR.po
odoo_addons/l10n_ec_config/i18n/en_GB.po
odoo_addons/l10n_ec_config/i18n/es.po
odoo_addons/l10n_ec_config/i18n/es_AR.po
odoo_addons/l10n_ec_config/i18n/es_CL.po
odoo_addons/l10n_ec_config/i18n/es_CO.po
odoo_addons/l10n_ec_config/i18n/es_CR.po
odoo_addons/l10n_ec_config/i18n/es_DO.po
odoo_addons/l10n_ec_config/i18n/es_EC.po
odoo_addons/l10n_ec_config/i18n/es_ES.po
odoo_addons/l10n_ec_config/i18n/es_MX.po
odoo_addons/l10n_ec_config/i18n/es_PE.po
odoo_addons/l10n_ec_config/i18n/es_PY.po
odoo_addons/l10n_ec_config/i18n/es_VE.po
odoo_addons/l10n_ec_config/i18n/et.po
odoo_addons/l10n_ec_config/i18n/eu.po
odoo_addons/l10n_ec_config/i18n/fa.po
odoo_addons/l10n_ec_config/i18n/fi.po
odoo_addons/l10n_ec_config/i18n/fr.po
odoo_addons/l10n_ec_config/i18n/fr_CA.po
odoo_addons/l10n_ec_config/i18n/fr_CH.po
odoo_addons/l10n_ec_config/i18n/gl.po
odoo_addons/l10n_ec_config/i18n/gl_ES.po
odoo_addons/l10n_ec_config/i18n/he.po
odoo_addons/l10n_ec_config/i18n/hr.po
odoo_addons/l10n_ec_config/i18n/hr_HR.po
odoo_addons/l10n_ec_config/i18n/hu.po
odoo_addons/l10n_ec_config/i18n/id.po
odoo_addons/l10n_ec_config/i18n/it.po
odoo_addons/l10n_ec_config/i18n/ja.po
odoo_addons/l10n_ec_config/i18n/ko.po
odoo_addons/l10n_ec_config/i18n/l10n_ec_config.pot
odoo_addons/l10n_ec_config/i18n/lt.po
odoo_addons/l10n_ec_config/i18n/lt_LT.po
odoo_addons/l10n_ec_config/i18n/lv.po
